smartoutlet/__init__.py
smartoutlet/ap7900.py
smartoutlet/ap7901.py
smartoutlet/ap790x.py
smartoutlet/cli.py
smartoutlet/daemon.py
smartoutlet/env.py
smartoutlet/http.py
smartoutlet/interface.py
smartoutlet/np_02.py
smartoutlet/np_02b.py
smartoutlet/np_05b.py
smartoutlet/np_08.py
smartoutlet/np_08b.py
smartoutlet/np_0x.py
smartoutlet/np_0xb.py
smartoutlet/py.typed
smartoutlet/snmp.py
smartoutlet-0.4.0.dist-info/LICENSE
smartoutlet-0.4.0.dist-info/METADATA
smartoutlet-0.4.0.dist-info/WHEEL
smartoutlet-0.4.0.dist-info/top_level.txt
smartoutlet-0.4.0.dist-info/RECORD
