Metadata-Version: 2.1
Name: smartoutlet
Version: 0.4.0
Summary: Collection of utilities for interfacing with various PDUs and smart outlets.
Home-page: https://github.com/DragonMinded/smartoutlet
Author: DragonMinded
Author-email: dragonminded@dragonminded.com
License: Public Domain
Requires-Python: >=3.6
License-File: LICENSE
Requires-Dist: requests
Requires-Dist: pyasyncore
Requires-Dist: pysnmplib
Requires-Dist: flask
